LICENSE.txt
MANIFEST.in
pyproject.toml
setup.cfg
setup.py
histoqc/AnnotationModule.py
histoqc/BaseImage.py
histoqc/BasicModule.py
histoqc/BlurDetectionModule.py
histoqc/BrightContrastModule.py
histoqc/BubbleRegionByRegion.py
histoqc/ClassificationModule.py
histoqc/DeconvolutionModule.py
histoqc/HistogramModule.py
histoqc/LightDarkModule.py
histoqc/LocalTextureEstimationModule.py
histoqc/MorphologyModule.py
histoqc/OmeroModule.py
histoqc/SaveModule.py
histoqc/__init__.py
histoqc/__main__.py
histoqc/_pipeline.py
histoqc/_worker.py
histoqc/config/__init__.py
histoqc/config/__main__.py
histoqc/config/config.ini
histoqc/config/config_clinical.ini
histoqc/config/config_first.ini
histoqc/config/config_ihc.ini
histoqc/config/config_light.ini
histoqc/config/config_v2.1.ini
histoqc/data/__init__.py
histoqc/data/__main__.py
histoqc/data/models/coverslip_edge_he/coverslip_edge.png
histoqc/data/models/coverslip_edge_he/coverslip_edge_mask.png
histoqc/data/models/coverslip_edge_ihc/coverslip_edge.png
histoqc/data/models/coverslip_edge_ihc/coverslip_edge_mask.png
histoqc/data/models/pen_markings_he/he.tsv
histoqc/data/models/pen_markings_he/pen_green.png
histoqc/data/models/pen_markings_he/pen_green_mask.png
histoqc/data/models/pen_markings_he/pen_red.png
histoqc/data/models/pen_markings_he/pen_red_mask.png
histoqc/data/pen/1k_version/pen_black.png
histoqc/data/pen/1k_version/pen_black_mask.png
histoqc/data/pen/1k_version/pen_green.png
histoqc/data/pen/1k_version/pen_green_mask.png
histoqc/data/pen/1k_version/pen_red.png
histoqc/data/pen/1k_version/pen_red_mask.png
histoqc/data/pen/1k_version/pen_red_mask_back.png
histoqc/data/pen/1k_version/red_mask.png
histoqc/data/templates/template1.png
histoqc/data/templates/template2.png
histoqc/data/templates/template3.png
histoqc/data/templates/template4.png
histoqc/ui/__init__.py
histoqc/ui/__main__.py
histoqc/ui/UserInterface/index.html
histoqc/ui/UserInterface/css/index.css
histoqcxomero.egg-info/PKG-INFO
histoqcxomero.egg-info/SOURCES.txt
histoqcxomero.egg-info/dependency_links.txt
histoqcxomero.egg-info/entry_points.txt
histoqcxomero.egg-info/requires.txt
histoqcxomero.egg-info/top_level.txt