Metadata-Version: 2.1
Name: histoqcxomero
Version: 0.20
Summary: HistoQCxOMERO is an open-source quality control tool for digital pathology slides, forked to run on omero api
Home-page: https://github.com/barrettMCW/HistoQCxOMERO
Author: Andrew Janowczyk, Michael Barrett
License: BSD
Download-URL: https://github.com/barrettMCW/HistoQCxOMERO
Platform: UNKNOWN
Classifier: Intended Audience :: Science/Research
Classifier: License :: OSI Approved :: BSD License
Classifier: Programming Language :: Python
Classifier: Programming Language :: Python :: 3 :: Only
Classifier: Programming Language :: Python :: 3.7
Classifier: Programming Language :: Python :: 3.8
Classifier: Programming Language :: Python :: 3.9
Classifier: Topic :: Scientific/Engineering
Classifier: Topic :: Scientific/Engineering :: Visualization
Classifier: Topic :: Scientific/Engineering :: Information Analysis
Classifier: Topic :: Scientific/Engineering :: Bio-Informatics
Classifier: Topic :: Utilities
Classifier: Operating System :: Microsoft :: Windows
Classifier: Operating System :: POSIX
Classifier: Operating System :: Unix
Classifier: Operating System :: MacOS
Requires-Python: >=3.7
Provides-Extra: tests
License-File: LICENSE.txt
